setup.py
gusset/__init__.py
gusset/colortable.py
gusset/output.py
gusset/validation.py
gusset.egg-info/PKG-INFO
gusset.egg-info/SOURCES.txt
gusset.egg-info/dependency_links.txt
gusset.egg-info/requires.txt
gusset.egg-info/top_level.txt