Metadata-Version: 1.0
Name: gusset
Version: 1.2
Summary: Small utilities for Fabric scripts.
Home-page: http://github.com/locationlabs/gusset
Author: Location Labs
Author-email: info@locationlabs.com
License: Apache2
Platform: UNKNOWN
